py2048/__init__.py
py2048/data.py
py2048/error.py
py2048/game.py
py2048/game.pyi
py2048/info.py
py2048/info.pyi
py2048/assets/Nevada.mp3
py2048/assets/P1024.png
py2048/assets/P128.png
py2048/assets/P16.png
py2048/assets/P2.png
py2048/assets/P2048.png
py2048/assets/P256.png
py2048/assets/P32.png
py2048/assets/P4.png
py2048/assets/P512.png
py2048/assets/P64.png
py2048/assets/P8.png
py2048/assets/SourceCodePro.ttf
py2048/data/ScoreList.json
py2048/info/LICENSE
py2048/info/README.md
python2048-1.0.0b1.dist-info/LICENSE
python2048-1.0.0b1.dist-info/METADATA
python2048-1.0.0b1.dist-info/WHEEL
python2048-1.0.0b1.dist-info/top_level.txt
python2048-1.0.0b1.dist-info/RECORD
