Metadata-Version: 2.2
Name: python2048
Version: 1.0.0b1
Summary: Python 2048
Home-page: https://github.com/BinaryGuo/Py2048
Author: GQX
Author-email: kill114514251@outlook.com
Classifier: Intended Audience :: End Users/Desktop
Classifier: Intended Audience :: Developers
Classifier: Development Status :: 4 - Beta
Classifier: Topic :: Software Development :: Libraries :: pygame
Classifier: Natural Language :: English
Classifier: Natural Language :: Chinese (Simplified)
Classifier: License :: OSI Approved :: MIT License
Classifier: Operating System :: OS Independent
Classifier: Programming Language :: Python :: 3.13
Classifier: Programming Language :: Python :: 3.12
Classifier: Programming Language :: Python :: 3.11
Classifier: Programming Language :: Python :: 3.10
Requires-Python: >=3.10
License-File: LICENSE
Requires-Dist: pygame>=2.5.0
Requires-Dist: pygame_menu>=4.5.0
Requires-Dist: pillow>=11.1.0
Dynamic: author
Dynamic: author-email
Dynamic: classifier
Dynamic: description
Dynamic: description-content-type
Dynamic: home-page
Dynamic: requires-dist
Dynamic: requires-python
Dynamic: summary
